semspaces/__init__.py
semspaces/space.py
semspaces/space_io.py
semspaces/utils.py
semspaces-0.1.5.data/scripts/csv_sims
semspaces-0.1.5.data/scripts/subset_space
semspaces-0.1.5.data/scripts/w2v2ssm
semspaces-0.1.5.dist-info/LICENSE
semspaces-0.1.5.dist-info/METADATA
semspaces-0.1.5.dist-info/WHEEL
semspaces-0.1.5.dist-info/top_level.txt
semspaces-0.1.5.dist-info/RECORD
