Metadata-Version: 2.1
Name: semspaces
Version: 0.1.5
Summary: Package for working with semantic spaces.
Home-page: https://github.com/pmandera/semspaces/
Author: Paweł Mandera
Author-email: pawel@pawelmandera.com
License: UNKNOWN
Keywords: semantic space word vectors
Platform: UNKNOWN
Classifier: Programming Language :: Python :: 3
Classifier: License :: OSI Approved :: Apache Software License
Requires-Dist: fs (>=0.5.0)
Requires-Dist: numpy (>=1.9.1)
Requires-Dist: scipy (>=0.14.0)
Requires-Dist: pandas (>=0.15.1)
Requires-Dist: scikit-learn (>=0.15.0)
